.gitignore
README.md
setup.py
douloader/__init__.py
douloader/dataloaders.py
douloader.egg-info/PKG-INFO
douloader.egg-info/SOURCES.txt
douloader.egg-info/dependency_links.txt
douloader.egg-info/top_level.txt