Metadata-Version: 2.1
Name: douloader
Version: 1.0.1
Summary: A multithreaded data loader for medical image data loading
Home-page: https://github.com/sanshitangmalaban/douloader
Author: sanshitangmalaban
Author-email: gs410406505ysu@163.com
License: UNKNOWN
Keywords: dataloader,multithreading
Platform: UNKNOWN
Classifier: Programming Language :: Python :: 3
Classifier: License :: OSI Approved :: MIT License
Classifier: Operating System :: OS Independent
